clearskies_gitlab/__init__.py
clearskies_gitlab/defaults/__init__.py
clearskies_gitlab/defaults/gitlab_default_auth.py
clearskies_gitlab/defaults/gitlab_default_host.py
clearskies_gitlab/defaults/gitlab_graphql_client.py
clearskies_gitlab/exceptions/__init__.py
clearskies_gitlab/exceptions/gitlab_error.py
clearskies_gitlab/graphql/__init__.py
clearskies_gitlab/graphql/backends/__init__.py
clearskies_gitlab/graphql/backends/gitlab_graphql_backend.py
clearskies_gitlab/graphql/models/__init__.py
clearskies_gitlab/graphql/models/gitlab_container_repository.py
clearskies_gitlab/graphql/models/gitlab_container_repository_reference.py
clearskies_gitlab/graphql/models/gitlab_container_repository_tag.py
clearskies_gitlab/graphql/models/gitlab_container_repository_tag_reference.py
clearskies_gitlab/graphql/models/gitlab_group.py
clearskies_gitlab/graphql/models/gitlab_group_reference.py
clearskies_gitlab/graphql/models/gitlab_project.py
clearskies_gitlab/graphql/models/gitlab_project_reference.py
clearskies_gitlab/rest/__init__.py
clearskies_gitlab/rest/gitlab_branch_rule.py
clearskies_gitlab/rest/gitlab_cicd_variable.py
clearskies_gitlab/rest/gitlab_member.py
clearskies_gitlab/rest/backends/__init__.py
clearskies_gitlab/rest/backends/gitlab_rest_backend.py
clearskies_gitlab/rest/models/__init__.py
clearskies_gitlab/rest/models/gitlab_rest_advanced_search.py
clearskies_gitlab/rest/models/gitlab_rest_advanced_search_blob.py
clearskies_gitlab/rest/models/gitlab_rest_current_user.py
clearskies_gitlab/rest/models/gitlab_rest_group.py
clearskies_gitlab/rest/models/gitlab_rest_group_access_token.py
clearskies_gitlab/rest/models/gitlab_rest_group_access_token_reference.py
clearskies_gitlab/rest/models/gitlab_rest_group_base.py
clearskies_gitlab/rest/models/gitlab_rest_group_member.py
clearskies_gitlab/rest/models/gitlab_rest_group_member_reference.py
clearskies_gitlab/rest/models/gitlab_rest_group_project.py
clearskies_gitlab/rest/models/gitlab_rest_group_project_reference.py
clear_skies_gitlab-2.0.7.dist-info/METADATA
clear_skies_gitlab-2.0.7.dist-info/WHEEL
clear_skies_gitlab-2.0.7.dist-info/licenses/LICENSE
clear_skies_gitlab-2.0.7.dist-info/RECORD
