Metadata-Version: 2.4
Name: clear-skies-gitlab
Version: 2.0.7
Summary: Gitlab module for Clearskies
Project-URL: Docs, https://https://clearskies.info/modules/clear-skies-gitlab
Project-URL: Repository, https://github.com/clearskies-py/gitlab
Project-URL: Issues, https://github.com/clearskies-py/gitlab/issues
Project-URL: Changelog, https://github.com/clearskies-py/gitlab/blob/main/CHANGELOG.md
Author-email: Tom Nijboer <tom.nijboer@cimpress.com>
License-Expression: MIT
License-File: LICENSE
Classifier: Development Status :: 5 - Production/Stable
Classifier: Intended Audience :: Developers
Classifier: License :: OSI Approved :: MIT License
Classifier: Programming Language :: Python :: 3
Requires-Python: <4.0,>=3.11
Requires-Dist: clear-skies>=2.0.0
Requires-Dist: gql[all]>=4.0.0
Requires-Dist: requests>=2.32.5
Provides-Extra: dev
Requires-Dist: types-requests>=2.32.4; extra == 'dev'
